config/__init__.py
config/config.py
domains/__init__.py
domains/historique.py
domains/issue.py
domains/synchronisation.py
files/__init__.py
files/correspondance_table.json
files/history.txt
implementations/__init__.py
implementations/implementation_historique.py
implementations/implementation_issue_S1.py
implementations/implementation_issue_S2.py
implementations/implementation_issue_S3.py
implementations/implementation_synchronisation_S1.py
implementations/implementation_synchronisation_S2.py
implementations/implementation_table_correpondance_key_id.py
log/__init__.py
log/file.log
synchros1s2-0.4.0.dist-info/METADATA
synchros1s2-0.4.0.dist-info/WHEEL
synchros1s2-0.4.0.dist-info/top_level.txt
synchros1s2-0.4.0.dist-info/RECORD
