Metadata-Version: 2.1
Name: synchros1s2
Version: 0.4.0
Summary: A small example package
Author: wefine
Author-email: wefine <wefine2529@ebuthor.com>
Classifier: Programming Language :: Python :: 3
Classifier: License :: OSI Approved :: MIT License
Classifier: Operating System :: OS Independent
